LICENSE
setup.py
py_simple_graphql/__init__.py
py_simple_graphql/class.py
py_simple_graphql/enums.py
py_simple_graphql/graphql.py
py_simple_graphql/graphql_config.py
py_simple_graphql/graphql_executor.py
py_simple_graphql/logger.py
py_simple_graphql/models.py
py_simple_graphql/query.py
py_simple_graphql/utils.py
py_simple_graphql.egg-info/PKG-INFO
py_simple_graphql.egg-info/SOURCES.txt
py_simple_graphql.egg-info/dependency_links.txt
py_simple_graphql.egg-info/requires.txt
py_simple_graphql.egg-info/top_level.txt
tests/__init__.py
tests/main.py
tests/models/__init__.py