Metadata-Version: 2.1
Name: py-simple-graphql
Version: 1.2.2
Summary: Simple work with GraphQL
Home-page: https://github.com/DephPhascow/py-graphql
Author: DephPhascow
Author-email: d.sinisterpsychologist@gmail.com
License: MIT Licence
Keywords: graphql
Platform: any
License-File: LICENSE
